taiga_contrib_slack/__init__.py
taiga_contrib_slack/api.py
taiga_contrib_slack/apps.py
taiga_contrib_slack/models.py
taiga_contrib_slack/permissions.py
taiga_contrib_slack/serializers.py
taiga_contrib_slack/signal_handlers.py
taiga_contrib_slack/tasks.py
taiga_contrib_slack/migrations/0001_initial.py
taiga_contrib_slack/migrations/0002_slackhook_channel.py
taiga_contrib_slack/migrations/0003_auto_20150923_1620.py
taiga_contrib_slack/migrations/0004_auto_20160914_1420.py
taiga_contrib_slack/migrations/__init__.py
taiga_contrib_slack/templates/taiga_contrib_slack/change.jinja
taiga_contrib_slack/templates/taiga_contrib_slack/create.jinja
taiga_contrib_slack/templates/taiga_contrib_slack/delete.jinja
taiga_contrib_slack/templates/taiga_contrib_slack/field-diff.jinja
taiga_contrib_slack-5.5.1.dist-info/LICENSE
taiga_contrib_slack-5.5.1.dist-info/METADATA
taiga_contrib_slack-5.5.1.dist-info/WHEEL
taiga_contrib_slack-5.5.1.dist-info/top_level.txt
taiga_contrib_slack-5.5.1.dist-info/RECORD
