Metadata-Version: 2.1
Name: taiga-contrib-slack
Version: 5.5.1
Summary: The Taiga plugin for slack integration
Home-page: https://github.com/taigaio/taiga-contrib-slack
Author: Jesús Espino García
Author-email: jesus.espino@kaleidos.net
License: AGPL
Keywords: taiga,slack,integration
Platform: UNKNOWN
Classifier: Programming Language :: Python
Classifier: Development Status :: 4 - Beta
Classifier: Framework :: Django
Classifier: Intended Audience :: Developers
Classifier: License :: OSI Approved :: GNU Affero General Public License v3
Classifier: Operating System :: OS Independent
Classifier: Programming Language :: Python
Classifier: Topic :: Internet :: WWW/HTTP
